osc_tiny-0.10.8.dist-info/licenses/LICENSE
osctiny/__init__.py
osctiny/osc.py
osctiny/extensions/__init__.py
osctiny/extensions/attributes.py
osctiny/extensions/bs_requests.py
osctiny/extensions/buildresults.py
osctiny/extensions/comments.py
osctiny/extensions/distributions.py
osctiny/extensions/issues.py
osctiny/extensions/origin.py
osctiny/extensions/packages.py
osctiny/extensions/projects.py
osctiny/extensions/search.py
osctiny/extensions/staging.py
osctiny/extensions/users.py
osctiny/models/__init__.py
osctiny/models/request.py
osctiny/models/staging.py
osctiny/tests/__init__.py
osctiny/tests/base.py
osctiny/tests/test_attributes.py
osctiny/tests/test_basic.py
osctiny/tests/test_build.py
osctiny/tests/test_comments.py
osctiny/tests/test_distributions.py
osctiny/tests/test_issues.py
osctiny/tests/test_origin.py
osctiny/tests/test_packages.py
osctiny/tests/test_projects.py
osctiny/tests/test_requests.py
osctiny/tests/test_search.py
osctiny/tests/test_staging.py
osctiny/tests/test_utils.py
osctiny/tests/osc/__init__.py
osctiny/tests/osc/conf.py
osctiny/utils/__init__.py
osctiny/utils/auth.py
osctiny/utils/backports.py
osctiny/utils/base.py
osctiny/utils/changelog.py
osctiny/utils/conf.py
osctiny/utils/cookies.py
osctiny/utils/errors.py
osctiny/utils/mapping.py
osctiny/utils/session.py
osctiny/utils/xml.py
osc_tiny-0.10.8.dist-info/METADATA
osc_tiny-0.10.8.dist-info/WHEEL
osc_tiny-0.10.8.dist-info/top_level.txt
osc_tiny-0.10.8.dist-info/RECORD
